hpbandster_sklearn/HpBandSterSearchCV.py
hpbandster_sklearn/SklearnWorker.py
hpbandster_sklearn/__init__.py
hpbandster_sklearn/booster_integration.py
hpbandster_sklearn/context.py
hpbandster_sklearn/search_cv.py
hpbandster_sklearn-2.0.2.dist-info/LICENSE
hpbandster_sklearn-2.0.2.dist-info/METADATA
hpbandster_sklearn-2.0.2.dist-info/WHEEL
hpbandster_sklearn-2.0.2.dist-info/top_level.txt
hpbandster_sklearn-2.0.2.dist-info/RECORD
