Metadata-Version: 2.1
Name: hpbandster-sklearn
Version: 2.0.2
Summary: A scikit-learn wrapper for HpBandSter hyper parameter search
Home-page: https://github.com/Yard1/hpbandster-sklearn
Author: Antoni Baum
Author-email: antoni.baum@protonmail.com
License: MIT
Keywords: distributed,optimization,multifidelity
Classifier: Programming Language :: Python :: 3
Classifier: Programming Language :: Python :: 3.6
Classifier: Programming Language :: Python :: 3.7
Classifier: License :: OSI Approved :: MIT License
Classifier: Operating System :: OS Independent
License-File: LICENSE
Requires-Dist: scikit-learn (>=0.24.0)
Requires-Dist: hpbandster
Requires-Dist: ConfigSpace
Requires-Dist: joblib
